[
  {
    "line": 1,
    "elements": [
      {
        "BDD_TESTRUN_UUID": "bcff943f-da6a-48f2-93eb-49c71d9cb1ae",
        "line": 49,
        "name": "Gonderim tipi Kagit ve Ihrac Kayitli tipinde e-Arsiv faturasi olusturulmasi",
        "description": "",
        "id": "gonderim-tipi-kagit-ve-ıhrac-kayitli-tipinde-e-arsiv-faturasi-olusturulmasi;gonderim-tipi-kagit-ve-ıhrac-kayitli-tipinde-e-arsiv-faturasi-olusturulmasi;;2",
        "type": "scenario",
        "keyword": "Scenario Outline",
        "steps": [
          {
            "result": {
              "duration": 15579369200,
              "status": "passed"
            },
            "line": 4,
            "name": "Kullanıcı adı EARIHRAC ve Şifre test1234 olarak giriş yapılır",
            "match": {
              "arguments": [
                {
                  "val": "EARIHRAC",
                  "offset": 14
                },
                {
                  "val": "test1234",
                  "offset": 32
                }
              ],
              "location": "girisSayfasi.login(String,String)"
            },
            "keyword": "* ",
            "BDD_STEP_UUID": "f7491452-9002-4100-a509-092fd741ab51"
          },
          {
            "result": {
              "duration": 631312700,
              "status": "passed"
            },
            "line": 5,
            "name": "Ana menüden e-Arşiv seçilir",
            "match": {
              "arguments": [
                {
                  "val": "e-Arşiv",
                  "offset": 12
                }
              ],
              "location": "menu.anaMenuSecimi(String)"
            },
            "keyword": "* ",
            "BDD_STEP_UUID": "eab28ade-a3e9-4c8e-afbe-84afedbc0dee"
          },
          {
            "result": {
              "duration": 3568010600,
              "status": "passed"
            },
            "line": 6,
            "name": "Alt menü e-Arşiv Araçları başlığı altındaki e-Arşiv Fatura Oluşturma seçilir",
            "match": {
              "arguments": [
                {
                  "val": "e-Arşiv Araçları",
                  "offset": 9
                },
                {
                  "val": "e-Arşiv Fatura Oluşturma",
                  "offset": 44
                }
              ],
              "location": "menu.basligaGoreAltMenuSecimi(String,String)"
            },
            "keyword": "* ",
            "BDD_STEP_UUID": "5f2be068-a800-47cc-b334-fcf331e6f91c"
          },
          {
            "result": {
              "duration": 4193951000,
              "status": "passed"
            },
            "line": 7,
            "name": "Tablodaki tüm veriler silinir",
            "match": {
              "location": "tablo.olusturmaTarihi()"
            },
            "keyword": "* ",
            "BDD_STEP_UUID": "9d2e11a7-de97-4f74-86ab-0ccaf604670e"
          },
          {
            "result": {
              "duration": 874252800,
              "status": "passed"
            },
            "line": 8,
            "name": "Butonlardan Ekle isimli butona tıklanır",
            "match": {
              "arguments": [
                {
                  "val": "Ekle",
                  "offset": 12
                }
              ],
              "location": "butonlar.butonaTikla(String)"
            },
            "keyword": "* ",
            "BDD_STEP_UUID": "70392070-d0ea-4e5f-a15c-f397599216ee"
          },
          {
            "result": {
              "duration": 6108579600,
              "status": "passed"
            },
            "line": 9,
            "name": "Görsel tasarım sayfasının e-Arşiv Fatura Bilgileri başlığını içerdiği kontrol edilir",
            "match": {
              "arguments": [
                {
                  "val": "e-Arşiv Fatura Bilgileri",
                  "offset": 26
                }
              ],
              "location": "genel.gorselTasarimSayfasininBasligindaVarMi(String)"
            },
            "keyword": "* ",
            "BDD_STEP_UUID": "e5a6a9f0-6f16-4a67-85b6-50622064e8d8"
          },
          {
            "result": {
              "duration": 6658347200,
              "status": "passed"
            },
            "line": 10,
            "name": "Alıcı adı alanına UC0004 girilir",
            "match": {
              "arguments": [
                {
                  "val": "UC0004",
                  "offset": 18
                }
              ],
              "location": "genel.aliciSec(String)"
            },
            "keyword": "* ",
            "BDD_STEP_UUID": "7329e08e-a906-4c08-aa87-c9faf0002c88"
          },
          {
            "result": {
              "duration": 1584905200,
              "status": "passed"
            },
            "line": 11,
            "name": "Gönderim Şekli Elektronik olarak seçilir",
            "match": {
              "arguments": [
                {
                  "val": "Elektronik",
                  "offset": 15
                }
              ],
              "location": "genel.gonderimSekliSecilir(String)"
            },
            "keyword": "* ",
            "BDD_STEP_UUID": "3f49b927-2ace-4ca5-856f-e90712f05eb4"
          },
          {
            "result": {
              "duration": 1480615300,
              "status": "passed"
            },
            "line": 12,
            "name": "Tip alanından İhraç Kayıtlı seçilir",
            "match": {
              "arguments": [
                {
                  "val": "İhraç Kayıtlı",
                  "offset": 14
                }
              ],
              "location": "genel.tipSecilir(String)"
            },
            "keyword": "* ",
            "BDD_STEP_UUID": "31feb3a2-4397-4a26-8818-6fbe33de1a90"
          },
          {
            "result": {
              "duration": 8243197400,
              "status": "passed"
            },
            "line": 13,
            "name": "Döküman Para Birimi alanından Türk Lirası seçilir",
            "match": {
              "arguments": [
                {
                  "val": "Türk Lirası",
                  "offset": 30
                }
              ],
              "location": "genel.dokumanParaBirimindenSecilir(String)"
            },
            "keyword": "* ",
            "BDD_STEP_UUID": "5834163c-dfe9-4706-9ce0-62f3abccf973"
          },
          {
            "result": {
              "duration": 1925143900,
              "status": "passed"
            },
            "line": 14,
            "name": "Ön Ek EAR olarak seçilir",
            "match": {
              "arguments": [
                {
                  "val": "EAR",
                  "offset": 6
                }
              ],
              "location": "genel.onEkSecilir(String)"
            },
            "keyword": "* ",
            "BDD_STEP_UUID": "e784cb87-d65b-4f44-8214-62ad1f1d9aff"
          },
          {
            "result": {
              "duration": 1547958000,
              "status": "passed"
            },
            "line": 15,
            "name": "Tasarım alanından Otomasyon seçilir",
            "match": {
              "arguments": [
                {
                  "val": "Otomasyon",
                  "offset": 18
                }
              ],
              "location": "genel.tasarimSecilir(String)"
            },
            "keyword": "* ",
            "BDD_STEP_UUID": "a26ed26c-b22f-4119-a403-d0a6a71450fb"
          },
          {
            "result": {
              "duration": 4707765000,
              "status": "passed"
            },
            "line": 16,
            "name": "Sipariş bilgileri UUC-SAT-1200001 ve 31.04.2020 olarak girilir",
            "match": {
              "arguments": [
                {
                  "val": "UUC-SAT-1200001",
                  "offset": 18
                },
                {
                  "val": "31.04.2020",
                  "offset": 37
                }
              ],
              "location": "genel.siparisBilgileri(String,String)"
            },
            "keyword": "* ",
            "BDD_STEP_UUID": "89948a90-0328-4d7e-b835-1bf2d1062ab4"
          },
          {
            "result": {
              "duration": 5178617500,
              "status": "passed"
            },
            "line": 17,
            "name": "İrsaliye Bilgileri AAAAAAAAAA,31.04.2020 olarak girilir",
            "match": {
              "arguments": [
                {
                  "val": "AAAAAAAAAA",
                  "offset": 19
                },
                {
                  "val": "31.04.2020",
                  "offset": 30
                }
              ],
              "location": "genel.irsaliyeBilgileriGirilir(String,String)"
            },
            "keyword": "* ",
            "BDD_STEP_UUID": "15ce9410-7587-4f57-979d-283288f99437"
          },
          {
            "result": {
              "duration": 1244357600,
              "status": "passed"
            },
            "line": 18,
            "name": "Ekle butonuna basılır",
            "match": {
              "location": "genel.ekleButonunaBasilir()"
            },
            "keyword": "* ",
            "BDD_STEP_UUID": "e9718cac-1ab4-4296-b1f0-5a1620c5b7c4"
          },
          {
            "result": {
              "duration": 2902626800,
              "status": "passed"
            },
            "line": 19,
            "name": "Ürün ekleme alanında Mal/Hizmet başlığına Otomasyon girilir",
            "match": {
              "arguments": [
                {
                  "val": "Mal/Hizmet",
                  "offset": 21
                },
                {
                  "val": "Otomasyon",
                  "offset": 42
                }
              ],
              "location": "genel.malzemeMalHizmetBilgileriGirilir(String,String)"
            },
            "keyword": "* ",
            "BDD_STEP_UUID": "05a80b10-9339-4b52-9be8-c16512a432f1"
          },
          {
            "result": {
              "duration": 2379224900,
              "status": "passed"
            },
            "line": 20,
            "name": "Ürün ekleme alanında Açıklaması başlığına Virgosol girilir",
            "match": {
              "arguments": [
                {
                  "val": "Açıklaması",
                  "offset": 21
                },
                {
                  "val": "Virgosol",
                  "offset": 42
                }
              ],
              "location": "genel.malzemeMalHizmetBilgileriGirilir(String,String)"
            },
            "keyword": "* ",
            "BDD_STEP_UUID": "68c10a97-24c3-4080-9239-c911aa4a0135"
          },
          {
            "result": {
              "duration": 2823572500,
              "status": "passed"
            },
            "line": 21,
            "name": "Ürün ekleme alanında Miktarı başlığına 400 girilir",
            "match": {
              "arguments": [
                {
                  "val": "Miktarı",
                  "offset": 21
                },
                {
                  "val": "400",
                  "offset": 39
                }
              ],
              "location": "genel.malzemeMalHizmetBilgileriGirilir(String,String)"
            },
            "keyword": "* ",
            "BDD_STEP_UUID": "9a1533ca-0afb-496d-9901-6680258ddd3b"
          },
          {
            "result": {
              "duration": 3373519100,
              "status": "passed"
            },
            "line": 22,
            "name": "Ürün ekleme alanında Birim Fiyat başlığına 100 girilir",
            "match": {
              "arguments": [
                {
                  "val": "Birim Fiyat",
                  "offset": 21
                },
                {
                  "val": "100",
                  "offset": 43
                }
              ],
              "location": "genel.malzemeMalHizmetBilgileriGirilir(String,String)"
            },
            "keyword": "* ",
            "BDD_STEP_UUID": "5fa09f71-5cdc-4413-80a6-dc0a30022793"
          },
          {
            "result": {
              "duration": 3699084500,
              "status": "passed"
            },
            "line": 23,
            "name": "Ürün ekleme alanında İskonto Oranı % başlığına 10 girilir",
            "match": {
              "arguments": [
                {
                  "val": "İskonto Oranı %",
                  "offset": 21
                },
                {
                  "val": "10",
                  "offset": 47
                }
              ],
              "location": "genel.malzemeMalHizmetBilgileriGirilir(String,String)"
            },
            "keyword": "* ",
            "BDD_STEP_UUID": "daba3637-13ee-40ed-8232-b978b1ba9996"
          },
          {
            "result": {
              "duration": 3923961000,
              "status": "passed"
            },
            "line": 24,
            "name": "Notlar alanına Otomasyon Not girilir",
            "match": {
              "arguments": [
                {
                  "val": "Otomasyon Not",
                  "offset": 15
                }
              ],
              "location": "genel.notGirilir(String)"
            },
            "keyword": "* ",
            "BDD_STEP_UUID": "6cd87a08-b824-4e76-9424-20ece0949975"
          },
          {
            "result": {
              "duration": 849136900,
              "status": "passed"
            },
            "line": 25,
            "name": "Ettn bilgisi kayıt edilir",
            "match": {
              "location": "genel.EttnBilgisiKayitEdilir()"
            },
            "keyword": "* ",
            "BDD_STEP_UUID": "6ca4a8c7-ea7b-47c7-8706-f7902a8e8dfa"
          },
          {
            "result": {
              "duration": 5118926000,
              "status": "passed"
            },
            "line": 26,
            "name": "Kaydet butonu seçilir",
            "match": {
              "location": "genel.kaydetSecilir()"
            },
            "keyword": "* ",
            "BDD_STEP_UUID": "43afe18e-91f1-431f-999d-c26cec927a4e"
          },
          {
            "result": {
              "duration": 750751800,
              "status": "passed"
            },
            "line": 27,
            "name": "Tabloda Ettn bilgisi kaydedilen veri oluşturuldu mu",
            "match": {
              "location": "tablo.tablodaEttnliVeriOlusturulduMu()"
            },
            "keyword": "* ",
            "BDD_STEP_UUID": "8e1d553a-b39a-4208-aa80-cb1a4e7b0e70"
          },
          {
            "result": {
              "duration": 932180300,
              "status": "passed"
            },
            "line": 28,
            "name": "Tablodan Ettn bilgisi kaydedilen veri seçilir",
            "match": {
              "location": "tablo.tablodanEttnliVeriSecilir()"
            },
            "keyword": "* ",
            "BDD_STEP_UUID": "eaa9353f-671f-4370-8486-bd5b15637e34"
          },
          {
            "result": {
              "duration": 878551000,
              "status": "passed"
            },
            "line": 29,
            "name": "Butonlardan Numara Oluştur isimli butona tıklanır",
            "match": {
              "arguments": [
                {
                  "val": "Numara Oluştur",
                  "offset": 12
                }
              ],
              "location": "butonlar.butonaTikla(String)"
            },
            "keyword": "* ",
            "BDD_STEP_UUID": "f341e898-78ef-4f1c-a6ad-a918e471cc8a"
          },
          {
            "result": {
              "duration": 1614566200,
              "status": "passed"
            },
            "line": 30,
            "name": "Popup mesajı Devam etmek istiyor musunuz içeriyor mu",
            "match": {
              "arguments": [
                {
                  "val": "Devam etmek istiyor musunuz",
                  "offset": 13
                }
              ],
              "location": "popup.popupIceriyorMu(String)"
            },
            "keyword": "* ",
            "BDD_STEP_UUID": "701e31a0-fb74-4822-b293-5d7f65087968"
          },
          {
            "result": {
              "duration": 840939200,
              "status": "passed"
            },
            "line": 31,
            "name": "Yönetim popupında Evet seçilir",
            "match": {
              "arguments": [
                {
                  "val": "Evet",
                  "offset": 18
                }
              ],
              "location": "popup.yonetimPopupindanSecilir(String)"
            },
            "keyword": "* ",
            "BDD_STEP_UUID": "707fed4c-1190-47fa-bfd3-dcd81ef7daeb"
          },
          {
            "result": {
              "duration": 1496779700,
              "status": "passed"
            },
            "line": 32,
            "name": "Popup mesajı oluşmuştur içeriyor mu",
            "match": {
              "arguments": [
                {
                  "val": "oluşmuştur",
                  "offset": 13
                }
              ],
              "location": "popup.popupIceriyorMu(String)"
            },
            "keyword": "* ",
            "BDD_STEP_UUID": "fc643c39-d353-4d77-a30d-43e7564ebae3"
          },
          {
            "result": {
              "duration": 603939400,
              "status": "passed"
            },
            "line": 33,
            "name": "Yönetim popupında Tamam seçilir",
            "match": {
              "arguments": [
                {
                  "val": "Tamam",
                  "offset": 18
                }
              ],
              "location": "popup.yonetimPopupindanSecilir(String)"
            },
            "keyword": "* ",
            "BDD_STEP_UUID": "47dc8587-ac42-464c-a2d9-95e649851fda"
          },
          {
            "result": {
              "duration": 1260961300,
              "status": "passed"
            },
            "line": 34,
            "name": "Tablodan Ettn bilgisi kaydedilen veri seçilir",
            "match": {
              "location": "tablo.tablodanEttnliVeriSecilir()"
            },
            "keyword": "* ",
            "BDD_STEP_UUID": "8be0708e-3ca7-4d4e-9513-be207db92845"
          },
          {
            "result": {
              "duration": 974793000,
              "status": "passed"
            },
            "line": 35,
            "name": "Butonlardan Gönder isimli butona tıklanır",
            "match": {
              "arguments": [
                {
                  "val": "Gönder",
                  "offset": 12
                }
              ],
              "location": "butonlar.butonaTikla(String)"
            },
            "keyword": "* ",
            "BDD_STEP_UUID": "ae55d898-f301-405d-80ac-a907478b9257"
          },
          {
            "result": {
              "duration": 1271987300,
              "status": "passed"
            },
            "line": 36,
            "name": "Popup mesajı Devam etmek istiyor musunuz içeriyor mu",
            "match": {
              "arguments": [
                {
                  "val": "Devam etmek istiyor musunuz",
                  "offset": 13
                }
              ],
              "location": "popup.popupIceriyorMu(String)"
            },
            "keyword": "* ",
            "BDD_STEP_UUID": "f6ef8ad1-5673-4a58-bcee-0d50cde87de8"
          },
          {
            "result": {
              "duration": 635205800,
              "status": "passed"
            },
            "line": 37,
            "name": "Yönetim popupında Evet seçilir",
            "match": {
              "arguments": [
                {
                  "val": "Evet",
                  "offset": 18
                }
              ],
              "location": "popup.yonetimPopupindanSecilir(String)"
            },
            "keyword": "* ",
            "BDD_STEP_UUID": "2860a17b-6c7d-4ddf-8cb4-792c9bf792be"
          },
          {
            "result": {
              "duration": 1344968200,
              "status": "passed"
            },
            "line": 38,
            "name": "Ana menüden e-Arşiv seçilir",
            "match": {
              "arguments": [
                {
                  "val": "e-Arşiv",
                  "offset": 12
                }
              ],
              "location": "menu.anaMenuSecimi(String)"
            },
            "keyword": "* ",
            "BDD_STEP_UUID": "0a18357d-df59-4087-86cd-7eac913ef36a"
          },
          {
            "result": {
              "duration": 2822543200,
              "status": "passed"
            },
            "line": 39,
            "name": "Alt menü e-Arşiv Hareketleri başlığı altındaki e-Arşiv Faturaları seçilir",
            "match": {
              "arguments": [
                {
                  "val": "e-Arşiv Hareketleri",
                  "offset": 9
                },
                {
                  "val": "e-Arşiv Faturaları",
                  "offset": 47
                }
              ],
              "location": "menu.basligaGoreAltMenuSecimi(String,String)"
            },
            "keyword": "* ",
            "BDD_STEP_UUID": "657708a9-bb71-4d3b-a71c-d78130904899"
          },
          {
            "result": {
              "duration": 1017579700,
              "status": "passed"
            },
            "line": 40,
            "name": "Filtrelerden Ettn filtresine Ettn bilgisi yaz",
            "match": {
              "location": "filtreler.filtreEttnYaz()"
            },
            "keyword": "* ",
            "BDD_STEP_UUID": "47d395a7-36f2-48b3-9b7c-321625656f15"
          },
          {
            "result": {
              "duration": 558446600,
              "status": "passed"
            },
            "line": 41,
            "name": "Filtre butonlarından Listele seçilir",
            "match": {
              "arguments": [
                {
                  "val": "Listele",
                  "offset": 21
                }
              ],
              "location": "filtreler.filtreButonSec(String)"
            },
            "keyword": "* ",
            "BDD_STEP_UUID": "a4d78aab-2252-4c7d-86ea-fdeb7881f03c"
          },
          {
            "result": {
              "duration": 750167300,
              "status": "passed"
            },
            "line": 42,
            "name": "Tabloda veri var mı kontrol edilir",
            "match": {
              "location": "tablo.tablodaVeriVarMi()"
            },
            "keyword": "* ",
            "BDD_STEP_UUID": "d04dde20-d6e7-4bae-8e5b-5e06374c4bb7"
          },
          {
            "result": {
              "duration": 777500400,
              "status": "passed"
            },
            "line": 44,
            "name": "Tabloda yeni oluşturulan eArsiv verisi başarılı mı",
            "match": {
              "location": "tablo.tablodaVeriBasariliMiArsiv()"
            },
            "keyword": "* ",
            "BDD_STEP_UUID": "a938aca0-6cc7-4432-8b64-575ae504997e"
          },
          {
            "result": {
              "duration": 3161983000,
              "status": "passed"
            },
            "line": 45,
            "name": "Kullanıcı işlemlerinden Çıkış seçilir",
            "match": {
              "arguments": [
                {
                  "val": "Çıkış",
                  "offset": 24
                }
              ],
              "location": "kullaniciIslemleri.kullaniciIslemi(String)"
            },
            "keyword": "* ",
            "BDD_STEP_UUID": "56dd7812-b7e9-4212-aac2-754059a33974"
          }
        ]
      }
    ],
    "name": "Gonderim tipi Kagit ve Ihrac Kayitli tipinde e-Arsiv faturasi olusturulmasi",
    "description": "",
    "id": "gonderim-tipi-kagit-ve-ıhrac-kayitli-tipinde-e-arsiv-faturasi-olusturulmasi",
    "keyword": "Feature",
    "uri": "C:/Users/DELL/Documents/GitHub/EES_KatalonLogo/Include/features/Regresyon/e-Arsiv/VKN-Elektronik-Ihrac Kayitli.feature",
    "tags": []
  }
]