[
  {
    "line": 1,
    "elements": [
      {
        "BDD_TESTRUN_UUID": "c1417d21-76c7-4fb4-9d33-50ace67d620d",
        "line": 52,
        "name": "Gonderim tipi Kagit ve Hal Satis tipinde e-Arsiv faturasi olusturulmasi",
        "description": "",
        "id": "gonderim-tipi-kagit-ve-hal-satis-tipinde-e-arsiv-faturasi-olusturulmasi;gonderim-tipi-kagit-ve-hal-satis-tipinde-e-arsiv-faturasi-olusturulmasi;;2",
        "type": "scenario",
        "keyword": "Scenario Outline",
        "steps": [
          {
            "result": {
              "duration": 10074574200,
              "status": "passed"
            },
            "line": 4,
            "name": "Kullanıcı adı HALSATIS ve Şifre test1234 olarak giriş yapılır",
            "match": {
              "arguments": [
                {
                  "val": "HALSATIS",
                  "offset": 14
                },
                {
                  "val": "test1234",
                  "offset": 32
                }
              ],
              "location": "girisSayfasi.login(String,String)"
            },
            "keyword": "* ",
            "BDD_STEP_UUID": "122c7198-4778-42ac-add0-a49477f8f194"
          },
          {
            "result": {
              "duration": 560381600,
              "status": "passed"
            },
            "line": 5,
            "name": "Ana menüden e-Arşiv seçilir",
            "match": {
              "arguments": [
                {
                  "val": "e-Arşiv",
                  "offset": 12
                }
              ],
              "location": "menu.anaMenuSecimi(String)"
            },
            "keyword": "* ",
            "BDD_STEP_UUID": "0075c51d-800a-4a8c-b82b-7b99d38ae30d"
          },
          {
            "result": {
              "duration": 4251573100,
              "status": "passed"
            },
            "line": 6,
            "name": "Alt menü e-Arşiv Araçları başlığı altındaki e-Arşiv Fatura Oluşturma seçilir",
            "match": {
              "arguments": [
                {
                  "val": "e-Arşiv Araçları",
                  "offset": 9
                },
                {
                  "val": "e-Arşiv Fatura Oluşturma",
                  "offset": 44
                }
              ],
              "location": "menu.basligaGoreAltMenuSecimi(String,String)"
            },
            "keyword": "* ",
            "BDD_STEP_UUID": "c33a5f22-fba6-4e23-83ff-2dc4570adee2"
          },
          {
            "result": {
              "duration": 4004708400,
              "status": "passed"
            },
            "line": 7,
            "name": "Tablodaki tüm veriler silinir",
            "match": {
              "location": "tablo.olusturmaTarihi()"
            },
            "keyword": "* ",
            "BDD_STEP_UUID": "ec91b002-247e-411b-bf4a-256873a98065"
          },
          {
            "result": {
              "duration": 904099000,
              "status": "passed"
            },
            "line": 8,
            "name": "Butonlardan Ekle isimli butona tıklanır",
            "match": {
              "arguments": [
                {
                  "val": "Ekle",
                  "offset": 12
                }
              ],
              "location": "butonlar.butonaTikla(String)"
            },
            "keyword": "* ",
            "BDD_STEP_UUID": "7b17d396-81e3-42e4-ad23-e606a48eb8a8"
          },
          {
            "result": {
              "duration": 7392594400,
              "status": "passed"
            },
            "line": 9,
            "name": "Görsel tasarım sayfasının e-Arşiv Fatura Bilgileri başlığını içerdiği kontrol edilir",
            "match": {
              "arguments": [
                {
                  "val": "e-Arşiv Fatura Bilgileri",
                  "offset": 26
                }
              ],
              "location": "genel.gorselTasarimSayfasininBasligindaVarMi(String)"
            },
            "keyword": "* ",
            "BDD_STEP_UUID": "27ec8dd3-4fd7-4a45-9bd3-f8db33e14a62"
          },
          {
            "result": {
              "duration": 7296603300,
              "status": "passed"
            },
            "line": 10,
            "name": "Alıcı adı alanına UC0002 girilir",
            "match": {
              "arguments": [
                {
                  "val": "UC0002",
                  "offset": 18
                }
              ],
              "location": "genel.aliciSec(String)"
            },
            "keyword": "* ",
            "BDD_STEP_UUID": "926f311b-ac06-4316-a5a3-48c3ff70ec10"
          },
          {
            "result": {
              "duration": 1802812100,
              "status": "passed"
            },
            "line": 11,
            "name": "Gönderim Şekli Elektronik olarak seçilir",
            "match": {
              "arguments": [
                {
                  "val": "Elektronik",
                  "offset": 15
                }
              ],
              "location": "genel.gonderimSekliSecilir(String)"
            },
            "keyword": "* ",
            "BDD_STEP_UUID": "e99370f9-7bcb-45c4-9b30-bf4998222127"
          },
          {
            "result": {
              "duration": 2336042300,
              "status": "passed"
            },
            "line": 12,
            "name": "Tip alanından Hal Satış seçilir",
            "match": {
              "arguments": [
                {
                  "val": "Hal Satış",
                  "offset": 14
                }
              ],
              "location": "genel.tipSecilir(String)"
            },
            "keyword": "* ",
            "BDD_STEP_UUID": "a5b41ffe-4b09-48de-88d8-a9448664fe65"
          },
          {
            "result": {
              "duration": 10302522700,
              "status": "passed"
            },
            "line": 13,
            "name": "Döküman Para Birimi alanından Türk Lirası seçilir",
            "match": {
              "arguments": [
                {
                  "val": "Türk Lirası",
                  "offset": 30
                }
              ],
              "location": "genel.dokumanParaBirimindenSecilir(String)"
            },
            "keyword": "* ",
            "BDD_STEP_UUID": "79a0fd35-b943-4422-aed1-ff44bd0fd92e"
          },
          {
            "result": {
              "duration": 1747396100,
              "status": "passed"
            },
            "line": 14,
            "name": "Ön Ek YIG olarak seçilir",
            "match": {
              "arguments": [
                {
                  "val": "YIG",
                  "offset": 6
                }
              ],
              "location": "genel.onEkSecilir(String)"
            },
            "keyword": "* ",
            "BDD_STEP_UUID": "799f582f-dd1a-4060-8abd-a8b0067371c9"
          },
          {
            "result": {
              "duration": 1602509100,
              "status": "passed"
            },
            "line": 15,
            "name": "Tasarım alanından Otomasyon seçilir",
            "match": {
              "arguments": [
                {
                  "val": "Otomasyon",
                  "offset": 18
                }
              ],
              "location": "genel.tasarimSecilir(String)"
            },
            "keyword": "* ",
            "BDD_STEP_UUID": "acd35cf0-f9bd-49f9-9085-b2f4397c76ef"
          },
          {
            "result": {
              "duration": 5023145300,
              "status": "passed"
            },
            "line": 16,
            "name": "Sipariş bilgileri UUC-SAT-1200001 ve 30.04.2020 olarak girilir",
            "match": {
              "arguments": [
                {
                  "val": "UUC-SAT-1200001",
                  "offset": 18
                },
                {
                  "val": "30.04.2020",
                  "offset": 37
                }
              ],
              "location": "genel.siparisBilgileri(String,String)"
            },
            "keyword": "* ",
            "BDD_STEP_UUID": "5926ca90-480a-4957-828f-bd46cffb75be"
          },
          {
            "result": {
              "duration": 5728235000,
              "status": "passed"
            },
            "line": 17,
            "name": "İrsaliye Bilgileri AAAAAAAAAA,30.04.2020 olarak girilir",
            "match": {
              "arguments": [
                {
                  "val": "AAAAAAAAAA",
                  "offset": 19
                },
                {
                  "val": "30.04.2020",
                  "offset": 30
                }
              ],
              "location": "genel.irsaliyeBilgileriGirilir(String,String)"
            },
            "keyword": "* ",
            "BDD_STEP_UUID": "b08f85c9-ba11-45c0-9384-e6e4dd2a914d"
          },
          {
            "result": {
              "duration": 1343843300,
              "status": "passed"
            },
            "line": 18,
            "name": "Ekle butonuna basılır",
            "match": {
              "location": "genel.ekleButonunaBasilir()"
            },
            "keyword": "* ",
            "BDD_STEP_UUID": "8e7fdb69-376a-4642-8f34-80d7b2c41fe3"
          },
          {
            "result": {
              "duration": 3136677200,
              "status": "passed"
            },
            "line": 19,
            "name": "Ürün ekleme alanında Mal/Hizmet başlığına Otomasyon girilir",
            "match": {
              "arguments": [
                {
                  "val": "Mal/Hizmet",
                  "offset": 21
                },
                {
                  "val": "Otomasyon",
                  "offset": 42
                }
              ],
              "location": "genel.malzemeMalHizmetBilgileriGirilir(String,String)"
            },
            "keyword": "* ",
            "BDD_STEP_UUID": "508dd349-2b9c-475d-bafc-8dc5809e61d6"
          },
          {
            "result": {
              "duration": 2288109900,
              "status": "passed"
            },
            "line": 20,
            "name": "Ürün ekleme alanında Açıklaması başlığına Virgosol girilir",
            "match": {
              "arguments": [
                {
                  "val": "Açıklaması",
                  "offset": 21
                },
                {
                  "val": "Virgosol",
                  "offset": 42
                }
              ],
              "location": "genel.malzemeMalHizmetBilgileriGirilir(String,String)"
            },
            "keyword": "* ",
            "BDD_STEP_UUID": "02919028-7b52-409d-bfce-262c5192b2f9"
          },
          {
            "result": {
              "duration": 2672741200,
              "status": "passed"
            },
            "line": 21,
            "name": "Ürün ekleme alanında Künye Numarası başlığına 1234567890123456789 girilir",
            "match": {
              "arguments": [
                {
                  "val": "Künye Numarası",
                  "offset": 21
                },
                {
                  "val": "1234567890123456789",
                  "offset": 46
                }
              ],
              "location": "genel.malzemeMalHizmetBilgileriGirilir(String,String)"
            },
            "keyword": "* ",
            "BDD_STEP_UUID": "b8431e45-2d12-408e-ad76-6d5a3a77207d"
          },
          {
            "result": {
              "duration": 2793542900,
              "status": "passed"
            },
            "line": 22,
            "name": "Ürün ekleme alanında Vkn/Tckn başlığına 11111111110 girilir",
            "match": {
              "arguments": [
                {
                  "val": "Vkn/Tckn",
                  "offset": 21
                },
                {
                  "val": "11111111110",
                  "offset": 40
                }
              ],
              "location": "genel.malzemeMalHizmetBilgileriGirilir(String,String)"
            },
            "keyword": "* ",
            "BDD_STEP_UUID": "ecad6c15-8b2e-4849-84cb-04c59c56ee36"
          },
          {
            "result": {
              "duration": 3185144600,
              "status": "passed"
            },
            "line": 23,
            "name": "Ürün ekleme alanında Mal Sahibi başlığına AAAAAAAAA girilir",
            "match": {
              "arguments": [
                {
                  "val": "Mal Sahibi",
                  "offset": 21
                },
                {
                  "val": "AAAAAAAAA",
                  "offset": 42
                }
              ],
              "location": "genel.malzemeMalHizmetBilgileriGirilir(String,String)"
            },
            "keyword": "* ",
            "BDD_STEP_UUID": "379846c2-374c-48ac-afe0-be2a13f09ec5"
          },
          {
            "result": {
              "duration": 3109140300,
              "status": "passed"
            },
            "line": 24,
            "name": "Ürün ekleme alanında Miktarı başlığına 400 girilir",
            "match": {
              "arguments": [
                {
                  "val": "Miktarı",
                  "offset": 21
                },
                {
                  "val": "400",
                  "offset": 39
                }
              ],
              "location": "genel.malzemeMalHizmetBilgileriGirilir(String,String)"
            },
            "keyword": "* ",
            "BDD_STEP_UUID": "687a1619-e852-4250-b773-271dfcf2efd2"
          },
          {
            "result": {
              "duration": 3718996900,
              "status": "passed"
            },
            "line": 25,
            "name": "Ürün ekleme alanında Birim Fiyat başlığına 100 girilir",
            "match": {
              "arguments": [
                {
                  "val": "Birim Fiyat",
                  "offset": 21
                },
                {
                  "val": "100",
                  "offset": 43
                }
              ],
              "location": "genel.malzemeMalHizmetBilgileriGirilir(String,String)"
            },
            "keyword": "* ",
            "BDD_STEP_UUID": "66f18da7-08f9-4860-96dc-53fada402e5f"
          },
          {
            "result": {
              "duration": 4101198900,
              "status": "passed"
            },
            "line": 26,
            "name": "Ürün ekleme alanında İskonto Oranı % başlığına 10 girilir",
            "match": {
              "arguments": [
                {
                  "val": "İskonto Oranı %",
                  "offset": 21
                },
                {
                  "val": "10",
                  "offset": 47
                }
              ],
              "location": "genel.malzemeMalHizmetBilgileriGirilir(String,String)"
            },
            "keyword": "* ",
            "BDD_STEP_UUID": "dcf0ee1c-7556-4a89-b4e6-b4247361a947"
          },
          {
            "result": {
              "duration": 5300650100,
              "status": "passed"
            },
            "line": 27,
            "name": "Notlar alanına Otomasyon Not girilir",
            "match": {
              "arguments": [
                {
                  "val": "Otomasyon Not",
                  "offset": 15
                }
              ],
              "location": "genel.notGirilir(String)"
            },
            "keyword": "* ",
            "BDD_STEP_UUID": "92d503d5-ae1b-4b71-9614-8b4cda4e85db"
          },
          {
            "result": {
              "duration": 942226400,
              "status": "passed"
            },
            "line": 28,
            "name": "Ettn bilgisi kayıt edilir",
            "match": {
              "location": "genel.EttnBilgisiKayitEdilir()"
            },
            "keyword": "* ",
            "BDD_STEP_UUID": "ea39ddd7-2658-4349-a7db-b0db6c573428"
          },
          {
            "result": {
              "duration": 5569813900,
              "status": "passed"
            },
            "line": 29,
            "name": "Kaydet butonu seçilir",
            "match": {
              "location": "genel.kaydetSecilir()"
            },
            "keyword": "* ",
            "BDD_STEP_UUID": "ac5905da-523c-4e64-8448-e9d188d90f3c"
          },
          {
            "result": {
              "duration": 721270700,
              "status": "passed"
            },
            "line": 30,
            "name": "Tabloda Ettn bilgisi kaydedilen veri oluşturuldu mu",
            "match": {
              "location": "tablo.tablodaEttnliVeriOlusturulduMu()"
            },
            "keyword": "* ",
            "BDD_STEP_UUID": "ca525645-5c67-4db9-a916-f13e421d2dea"
          },
          {
            "result": {
              "duration": 1098066300,
              "status": "passed"
            },
            "line": 31,
            "name": "Tablodan Ettn bilgisi kaydedilen veri seçilir",
            "match": {
              "location": "tablo.tablodanEttnliVeriSecilir()"
            },
            "keyword": "* ",
            "BDD_STEP_UUID": "fbb4e6ed-da84-4ce9-91fd-428f1f699c8b"
          },
          {
            "result": {
              "duration": 935132200,
              "status": "passed"
            },
            "line": 32,
            "name": "Butonlardan Numara Oluştur isimli butona tıklanır",
            "match": {
              "arguments": [
                {
                  "val": "Numara Oluştur",
                  "offset": 12
                }
              ],
              "location": "butonlar.butonaTikla(String)"
            },
            "keyword": "* ",
            "BDD_STEP_UUID": "63053e88-6330-4afa-b4fe-07ff2885bd19"
          },
          {
            "result": {
              "duration": 1690007500,
              "status": "passed"
            },
            "line": 33,
            "name": "Popup mesajı Devam etmek istiyor musunuz içeriyor mu",
            "match": {
              "arguments": [
                {
                  "val": "Devam etmek istiyor musunuz",
                  "offset": 13
                }
              ],
              "location": "popup.popupIceriyorMu(String)"
            },
            "keyword": "* ",
            "BDD_STEP_UUID": "e1f4d8d5-9c05-41ef-91d0-c427ce1dcaa4"
          },
          {
            "result": {
              "duration": 825891800,
              "status": "passed"
            },
            "line": 34,
            "name": "Yönetim popupında Evet seçilir",
            "match": {
              "arguments": [
                {
                  "val": "Evet",
                  "offset": 18
                }
              ],
              "location": "popup.yonetimPopupindanSecilir(String)"
            },
            "keyword": "* ",
            "BDD_STEP_UUID": "410f5dca-1ba3-4140-9562-838b12fb01bb"
          },
          {
            "result": {
              "duration": 1909029600,
              "status": "passed"
            },
            "line": 35,
            "name": "Popup mesajı oluşmuştur içeriyor mu",
            "match": {
              "arguments": [
                {
                  "val": "oluşmuştur",
                  "offset": 13
                }
              ],
              "location": "popup.popupIceriyorMu(String)"
            },
            "keyword": "* ",
            "BDD_STEP_UUID": "1230fe95-0cac-4186-825f-4d63962a6e5b"
          },
          {
            "result": {
              "duration": 611307600,
              "status": "passed"
            },
            "line": 36,
            "name": "Yönetim popupında Tamam seçilir",
            "match": {
              "arguments": [
                {
                  "val": "Tamam",
                  "offset": 18
                }
              ],
              "location": "popup.yonetimPopupindanSecilir(String)"
            },
            "keyword": "* ",
            "BDD_STEP_UUID": "ff3e0208-565d-4c43-923e-408d0f4bb807"
          },
          {
            "result": {
              "duration": 1560468900,
              "status": "passed"
            },
            "line": 37,
            "name": "Tablodan Ettn bilgisi kaydedilen veri seçilir",
            "match": {
              "location": "tablo.tablodanEttnliVeriSecilir()"
            },
            "keyword": "* ",
            "BDD_STEP_UUID": "2c669f9c-3401-451b-8dc4-2d9774990d99"
          },
          {
            "result": {
              "duration": 1253481800,
              "status": "passed"
            },
            "line": 38,
            "name": "Butonlardan Gönder isimli butona tıklanır",
            "match": {
              "arguments": [
                {
                  "val": "Gönder",
                  "offset": 12
                }
              ],
              "location": "butonlar.butonaTikla(String)"
            },
            "keyword": "* ",
            "BDD_STEP_UUID": "7cf437ce-78c7-42fc-815f-af1f89fbf734"
          },
          {
            "result": {
              "duration": 1475276200,
              "status": "passed"
            },
            "line": 39,
            "name": "Popup mesajı Devam etmek istiyor musunuz içeriyor mu",
            "match": {
              "arguments": [
                {
                  "val": "Devam etmek istiyor musunuz",
                  "offset": 13
                }
              ],
              "location": "popup.popupIceriyorMu(String)"
            },
            "keyword": "* ",
            "BDD_STEP_UUID": "db49d508-62ea-447c-9f7c-d7f54e90562f"
          },
          {
            "result": {
              "duration": 605523400,
              "status": "passed"
            },
            "line": 40,
            "name": "Yönetim popupında Evet seçilir",
            "match": {
              "arguments": [
                {
                  "val": "Evet",
                  "offset": 18
                }
              ],
              "location": "popup.yonetimPopupindanSecilir(String)"
            },
            "keyword": "* ",
            "BDD_STEP_UUID": "a6ae8642-a00b-4614-adba-b6c2688dc6fd"
          },
          {
            "result": {
              "duration": 1259583800,
              "status": "passed"
            },
            "line": 41,
            "name": "Ana menüden e-Arşiv seçilir",
            "match": {
              "arguments": [
                {
                  "val": "e-Arşiv",
                  "offset": 12
                }
              ],
              "location": "menu.anaMenuSecimi(String)"
            },
            "keyword": "* ",
            "BDD_STEP_UUID": "d3fd5f2e-59b6-4bdc-8104-f06e75e58841"
          },
          {
            "result": {
              "duration": 2209725800,
              "status": "passed"
            },
            "line": 42,
            "name": "Alt menü e-Arşiv Hareketleri başlığı altındaki e-Arşiv Faturaları seçilir",
            "match": {
              "arguments": [
                {
                  "val": "e-Arşiv Hareketleri",
                  "offset": 9
                },
                {
                  "val": "e-Arşiv Faturaları",
                  "offset": 47
                }
              ],
              "location": "menu.basligaGoreAltMenuSecimi(String,String)"
            },
            "keyword": "* ",
            "BDD_STEP_UUID": "6eb9a0eb-91e2-463d-a996-c0505e9d433d"
          },
          {
            "result": {
              "duration": 1923874500,
              "status": "passed"
            },
            "line": 43,
            "name": "Filtrelerden Ettn filtresine Ettn bilgisi yaz",
            "match": {
              "location": "filtreler.filtreEttnYaz()"
            },
            "keyword": "* ",
            "BDD_STEP_UUID": "0b8493ae-a9d2-44a2-826c-3e95447b8383"
          },
          {
            "result": {
              "duration": 620991200,
              "status": "passed"
            },
            "line": 44,
            "name": "Filtre butonlarından Listele seçilir",
            "match": {
              "arguments": [
                {
                  "val": "Listele",
                  "offset": 21
                }
              ],
              "location": "filtreler.filtreButonSec(String)"
            },
            "keyword": "* ",
            "BDD_STEP_UUID": "40a5a019-f7aa-411a-a6d3-486981257920"
          },
          {
            "result": {
              "duration": 1214817300,
              "status": "passed"
            },
            "line": 45,
            "name": "Tabloda veri var mı kontrol edilir",
            "match": {
              "location": "tablo.tablodaVeriVarMi()"
            },
            "keyword": "* ",
            "BDD_STEP_UUID": "3e16d2d4-1f0b-4077-8d9d-f4bd8968626f"
          },
          {
            "result": {
              "duration": 921032300,
              "status": "passed"
            },
            "line": 47,
            "name": "Tabloda yeni oluşturulan eArsiv verisi başarılı mı",
            "match": {
              "location": "tablo.tablodaVeriBasariliMiArsiv()"
            },
            "keyword": "* ",
            "BDD_STEP_UUID": "713d5123-cc51-4e4a-bc32-c2117364522c"
          },
          {
            "result": {
              "duration": 3750063700,
              "status": "passed"
            },
            "line": 48,
            "name": "Kullanıcı işlemlerinden Çıkış seçilir",
            "match": {
              "arguments": [
                {
                  "val": "Çıkış",
                  "offset": 24
                }
              ],
              "location": "kullaniciIslemleri.kullaniciIslemi(String)"
            },
            "keyword": "* ",
            "BDD_STEP_UUID": "d4f8f44a-65a5-4580-94aa-9ba2f4ca5b76"
          }
        ]
      }
    ],
    "name": "Gonderim tipi Kagit ve Hal Satis tipinde e-Arsiv faturasi olusturulmasi",
    "description": "",
    "id": "gonderim-tipi-kagit-ve-hal-satis-tipinde-e-arsiv-faturasi-olusturulmasi",
    "keyword": "Feature",
    "uri": "C:/Users/DELL/Documents/GitHub/EES_KatalonLogo/Include/features/Regresyon/e-Arsiv/VKN-Elektronik-Hal Satis.feature",
    "tags": []
  }
]