[
  {
    "line": 1,
    "elements": [
      {
        "BDD_TESTRUN_UUID": "b8706456-ce03-4bdb-abe9-c759bd17dea4",
        "line": 46,
        "name": "Giden Kutusu Irsaliye Yanitlari Buton Kontrolu",
        "description": "",
        "id": "giden-kutusu-ırsaliye-yanitlari-buton-kontrolu;giden-kutusu-ırsaliye-yanitlari-buton-kontrolu;;2",
        "type": "scenario",
        "keyword": "Scenario Outline",
        "steps": [
          {
            "result": {
              "duration": 13092120300,
              "status": "passed"
            },
            "line": 4,
            "name": "Kullanıcı adı ELOGO6 ve Şifre 123456 olarak giriş yapılır",
            "match": {
              "arguments": [
                {
                  "val": "ELOGO6",
                  "offset": 14
                },
                {
                  "val": "123456",
                  "offset": 30
                }
              ],
              "location": "girisSayfasi.login(String,String)"
            },
            "keyword": "* ",
            "BDD_STEP_UUID": "9e60d5f3-369c-4089-b02f-7009fc237a42"
          },
          {
            "result": {
              "duration": 602072600,
              "status": "passed"
            },
            "line": 5,
            "name": "Ana menüden e-İrsaliye seçilir",
            "match": {
              "arguments": [
                {
                  "val": "e-İrsaliye",
                  "offset": 12
                }
              ],
              "location": "menu.anaMenuSecimi(String)"
            },
            "keyword": "* ",
            "BDD_STEP_UUID": "c951cba3-db1e-4e25-b0e2-ca4bbdc9b7bd"
          },
          {
            "result": {
              "duration": 3907339100,
              "status": "passed"
            },
            "line": 6,
            "name": "Alt menü Giden Kutusu başlığı altındaki İrsaliye Yanıtları seçilir",
            "match": {
              "arguments": [
                {
                  "val": "Giden Kutusu",
                  "offset": 9
                },
                {
                  "val": "İrsaliye Yanıtları",
                  "offset": 40
                }
              ],
              "location": "menu.basligaGoreAltMenuSecimi(String,String)"
            },
            "keyword": "* ",
            "BDD_STEP_UUID": "f182cc22-5247-4fff-85af-9a68413acf94"
          },
          {
            "result": {
              "duration": 1941072100,
              "status": "passed"
            },
            "line": 7,
            "name": "Filtrelerden Oluşturma Tarihi filtresine 01.01.2020 baslangic degerini yaz",
            "match": {
              "arguments": [
                {
                  "val": "Oluşturma Tarihi",
                  "offset": 13
                },
                {
                  "val": "01.01.2020",
                  "offset": 41
                }
              ],
              "location": "filtreler.filtreBaslangicYaz(String,String)"
            },
            "keyword": "* ",
            "BDD_STEP_UUID": "98d43d23-dd7a-4611-8b68-73232505bb58"
          },
          {
            "result": {
              "duration": 2110024300,
              "status": "passed"
            },
            "line": 8,
            "name": "Filtrelerden Oluşturma Tarihi filtresine 31.12.2020 bitis degerini yaz",
            "match": {
              "arguments": [
                {
                  "val": "Oluşturma Tarihi",
                  "offset": 13
                },
                {
                  "val": "31.12.2020",
                  "offset": 41
                }
              ],
              "location": "filtreler.filtreBitisYaz(String,String)"
            },
            "keyword": "* ",
            "BDD_STEP_UUID": "6cfb1d84-7f39-413f-88d5-359e3e61bf53"
          },
          {
            "result": {
              "duration": 740963800,
              "status": "passed"
            },
            "line": 9,
            "name": "Filtre butonlarından Listele seçilir",
            "match": {
              "arguments": [
                {
                  "val": "Listele",
                  "offset": 21
                }
              ],
              "location": "filtreler.filtreButonSec(String)"
            },
            "keyword": "* ",
            "BDD_STEP_UUID": "d8c7984d-aada-427d-81f7-40f072f8d038"
          },
          {
            "result": {
              "duration": 1245193500,
              "status": "passed"
            },
            "line": 10,
            "name": "Tablodan Logo Elektronik GIB Test isimli verinin detayı tıklanır",
            "match": {
              "arguments": [
                {
                  "val": "Logo Elektronik GIB Test",
                  "offset": 9
                }
              ],
              "location": "tablo.tablodakiVerininDetayi(String)"
            },
            "keyword": "* ",
            "BDD_STEP_UUID": "baec25df-bcc5-4c29-b2a3-e573d46c8607"
          },
          {
            "result": {
              "duration": 1104706500,
              "status": "passed"
            },
            "line": 11,
            "name": "Tablodan Logo Elektronik GIB Test isimli verinin detayı tıklanır",
            "match": {
              "arguments": [
                {
                  "val": "Logo Elektronik GIB Test",
                  "offset": 9
                }
              ],
              "location": "tablo.tablodakiVerininDetayi(String)"
            },
            "keyword": "* ",
            "BDD_STEP_UUID": "b033cbfe-1ae2-46c2-8a90-f4349b32fa03"
          },
          {
            "result": {
              "duration": 727851200,
              "status": "passed"
            },
            "line": 12,
            "name": "Filtre alanlarında Alıcı Ünvanı var mı",
            "match": {
              "arguments": [
                {
                  "val": "Alıcı Ünvanı",
                  "offset": 19
                }
              ],
              "location": "filtreler.filtreVarMi(String)"
            },
            "keyword": "* ",
            "BDD_STEP_UUID": "be84f5c2-9751-4d80-81c3-f0508e023f07"
          },
          {
            "result": {
              "duration": 480155500,
              "status": "passed"
            },
            "line": 13,
            "name": "Filtre alanlarında Alıcı VKN/TCKN var mı",
            "match": {
              "arguments": [
                {
                  "val": "Alıcı VKN/TCKN",
                  "offset": 19
                }
              ],
              "location": "filtreler.filtreVarMi(String)"
            },
            "keyword": "* ",
            "BDD_STEP_UUID": "9cbf8766-eb0c-4f31-ac86-0ea8223293c7"
          },
          {
            "result": {
              "duration": 505009500,
              "status": "passed"
            },
            "line": 14,
            "name": "Filtre alanlarında İrsaliye Yanıtı No var mı",
            "match": {
              "arguments": [
                {
                  "val": "İrsaliye Yanıtı No",
                  "offset": 19
                }
              ],
              "location": "filtreler.filtreVarMi(String)"
            },
            "keyword": "* ",
            "BDD_STEP_UUID": "df152722-f15a-47e7-8516-ba6f9d99f628"
          },
          {
            "result": {
              "duration": 511486400,
              "status": "passed"
            },
            "line": 15,
            "name": "Filtre alanlarında İrsaliye Yanıtı ETTN var mı",
            "match": {
              "arguments": [
                {
                  "val": "İrsaliye Yanıtı ETTN",
                  "offset": 19
                }
              ],
              "location": "filtreler.filtreVarMi(String)"
            },
            "keyword": "* ",
            "BDD_STEP_UUID": "8d35787a-3a95-44f8-b276-aaaefd84799e"
          },
          {
            "result": {
              "duration": 476364400,
              "status": "passed"
            },
            "line": 16,
            "name": "Filtre alanlarında Oluşturma Tarihi var mı",
            "match": {
              "arguments": [
                {
                  "val": "Oluşturma Tarihi",
                  "offset": 19
                }
              ],
              "location": "filtreler.filtreVarMi(String)"
            },
            "keyword": "* ",
            "BDD_STEP_UUID": "0ec23ef8-84a0-4771-80bc-da8590ff6253"
          },
          {
            "result": {
              "duration": 479664100,
              "status": "passed"
            },
            "line": 17,
            "name": "Filtre alanlarında Belge Tarihi var mı",
            "match": {
              "arguments": [
                {
                  "val": "Belge Tarihi",
                  "offset": 19
                }
              ],
              "location": "filtreler.filtreVarMi(String)"
            },
            "keyword": "* ",
            "BDD_STEP_UUID": "2a0b4570-890b-4b08-adcf-bcab770d122e"
          },
          {
            "result": {
              "duration": 553510000,
              "status": "passed"
            },
            "line": 18,
            "name": "Filtre alanlarında İlşk. İrsaliye No var mı",
            "match": {
              "arguments": [
                {
                  "val": "İlşk. İrsaliye No",
                  "offset": 19
                }
              ],
              "location": "filtreler.filtreVarMi(String)"
            },
            "keyword": "* ",
            "BDD_STEP_UUID": "2b2ba20d-a579-42b1-ab75-1dd0b27c3ed4"
          },
          {
            "result": {
              "duration": 611272900,
              "status": "passed"
            },
            "line": 19,
            "name": "Filtre alanlarında İlşk. İrsaliye ETTN var mı",
            "match": {
              "arguments": [
                {
                  "val": "İlşk. İrsaliye ETTN",
                  "offset": 19
                }
              ],
              "location": "filtreler.filtreVarMi(String)"
            },
            "keyword": "* ",
            "BDD_STEP_UUID": "f7399f40-c46f-42b4-9051-8901f012cad8"
          },
          {
            "result": {
              "duration": 549077300,
              "status": "passed"
            },
            "line": 21,
            "name": "Filtre alanlarında Kullanıcı Kodu var mı",
            "match": {
              "arguments": [
                {
                  "val": "Kullanıcı Kodu",
                  "offset": 19
                }
              ],
              "location": "filtreler.filtreVarMi(String)"
            },
            "keyword": "* ",
            "BDD_STEP_UUID": "68072db3-5403-49d1-b28e-8b83bc681b0e"
          },
          {
            "result": {
              "duration": 565638900,
              "status": "passed"
            },
            "line": 22,
            "name": "Filtre alanlarında Zarf ETTN var mı",
            "match": {
              "arguments": [
                {
                  "val": "Zarf ETTN",
                  "offset": 19
                }
              ],
              "location": "filtreler.filtreVarMi(String)"
            },
            "keyword": "* ",
            "BDD_STEP_UUID": "7e930c71-d8fe-4d77-94fb-c4e43979888b"
          },
          {
            "result": {
              "duration": 527766200,
              "status": "passed"
            },
            "line": 23,
            "name": "Filtre alanlarında Atanan Departman var mı",
            "match": {
              "arguments": [
                {
                  "val": "Atanan Departman",
                  "offset": 19
                }
              ],
              "location": "filtreler.filtreVarMi(String)"
            },
            "keyword": "* ",
            "BDD_STEP_UUID": "15f74530-4f28-4710-b283-64b400bd0363"
          },
          {
            "result": {
              "duration": 455395800,
              "status": "passed"
            },
            "line": 24,
            "name": "Filtre butonlarında Filtreleri Kaydet var mı",
            "match": {
              "arguments": [
                {
                  "val": "Filtreleri Kaydet",
                  "offset": 20
                }
              ],
              "location": "filtreler.butonVarMi(String)"
            },
            "keyword": "* ",
            "BDD_STEP_UUID": "a74c965a-a0f5-4355-8ab1-dc16d3e8b750"
          },
          {
            "result": {
              "duration": 458176600,
              "status": "passed"
            },
            "line": 25,
            "name": "Filtre butonlarında Listele var mı",
            "match": {
              "arguments": [
                {
                  "val": "Listele",
                  "offset": 20
                }
              ],
              "location": "filtreler.butonVarMi(String)"
            },
            "keyword": "* ",
            "BDD_STEP_UUID": "7da1db5d-bc65-4256-b7c3-4ac2ee318ffd"
          },
          {
            "result": {
              "duration": 461965100,
              "status": "passed"
            },
            "line": 26,
            "name": "Filtre butonlarında Temizle var mı",
            "match": {
              "arguments": [
                {
                  "val": "Temizle",
                  "offset": 20
                }
              ],
              "location": "filtreler.butonVarMi(String)"
            },
            "keyword": "* ",
            "BDD_STEP_UUID": "4a3ba223-a375-466c-a58b-7f838245e204"
          },
          {
            "result": {
              "duration": 461294800,
              "status": "passed"
            },
            "line": 27,
            "name": "Butonlardan Excel var mı",
            "match": {
              "arguments": [
                {
                  "val": "Excel",
                  "offset": 12
                }
              ],
              "location": "butonlar.butonVarMi(String)"
            },
            "keyword": "* ",
            "BDD_STEP_UUID": "4326ce96-4f62-4d07-bcdd-94468b21d170"
          },
          {
            "result": {
              "duration": 445573800,
              "status": "passed"
            },
            "line": 28,
            "name": "Butonlardan Toplu İndirme var mı",
            "match": {
              "arguments": [
                {
                  "val": "Toplu İndirme",
                  "offset": 12
                }
              ],
              "location": "butonlar.butonVarMi(String)"
            },
            "keyword": "* ",
            "BDD_STEP_UUID": "2bb6395c-7180-4520-b16f-e75061d632a3"
          },
          {
            "result": {
              "duration": 555216200,
              "status": "passed"
            },
            "line": 29,
            "name": "Butonlardan UBL var mı",
            "match": {
              "arguments": [
                {
                  "val": "UBL",
                  "offset": 12
                }
              ],
              "location": "butonlar.butonVarMi(String)"
            },
            "keyword": "* ",
            "BDD_STEP_UUID": "dfc51601-d564-4792-8003-acf2b2aa05a5"
          },
          {
            "result": {
              "duration": 631945900,
              "status": "passed"
            },
            "line": 30,
            "name": "Butonlardan İzleme Kayıtları var mı",
            "match": {
              "arguments": [
                {
                  "val": "İzleme Kayıtları",
                  "offset": 12
                }
              ],
              "location": "butonlar.butonVarMi(String)"
            },
            "keyword": "* ",
            "BDD_STEP_UUID": "2e0d9a40-c541-43be-a6ef-6b03eea240bc"
          },
          {
            "result": {
              "duration": 484000400,
              "status": "passed"
            },
            "line": 31,
            "name": "Butonlardan Departman Ata var mı",
            "match": {
              "arguments": [
                {
                  "val": "Departman Ata",
                  "offset": 12
                }
              ],
              "location": "butonlar.butonVarMi(String)"
            },
            "keyword": "* ",
            "BDD_STEP_UUID": "ed1b4cd6-6f24-4b99-b97a-75057a3c6106"
          },
          {
            "result": {
              "duration": 498385600,
              "status": "passed"
            },
            "line": 32,
            "name": "Butonlardan Departman Geri Al var mı",
            "match": {
              "arguments": [
                {
                  "val": "Departman Geri Al",
                  "offset": 12
                }
              ],
              "location": "butonlar.butonVarMi(String)"
            },
            "keyword": "* ",
            "BDD_STEP_UUID": "d8555d95-7fc0-473b-a6b2-a561cf9a7dc2"
          },
          {
            "result": {
              "duration": 640584900,
              "status": "passed"
            },
            "line": 33,
            "name": "Butonlardan Excel isimli butona tıklanır",
            "match": {
              "arguments": [
                {
                  "val": "Excel",
                  "offset": 12
                }
              ],
              "location": "butonlar.butonaTikla(String)"
            },
            "keyword": "* ",
            "BDD_STEP_UUID": "d0620398-6385-4ea8-994e-c0f417fad5a4"
          },
          {
            "result": {
              "duration": 471909100,
              "status": "passed"
            },
            "line": 34,
            "name": "Alt butonlardan Excel\u0027e Aktar var mı",
            "match": {
              "arguments": [
                {
                  "val": "Excel\u0027e Aktar",
                  "offset": 16
                }
              ],
              "location": "butonlar.altButonVarMi(String)"
            },
            "keyword": "* ",
            "BDD_STEP_UUID": "297657cd-1967-46a9-9d1e-314b84f45807"
          },
          {
            "result": {
              "duration": 421803200,
              "status": "passed"
            },
            "line": 35,
            "name": "Alt butonlardan Tümünü Excel\u0027e Aktar var mı",
            "match": {
              "arguments": [
                {
                  "val": "Tümünü Excel\u0027e Aktar",
                  "offset": 16
                }
              ],
              "location": "butonlar.altButonVarMi(String)"
            },
            "keyword": "* ",
            "BDD_STEP_UUID": "6cf356b0-83e5-4d16-be32-2a896d3eff2d"
          },
          {
            "result": {
              "duration": 517551900,
              "status": "passed"
            },
            "line": 36,
            "name": "Butonlardan Toplu İndirme isimli butona tıklanır",
            "match": {
              "arguments": [
                {
                  "val": "Toplu İndirme",
                  "offset": 12
                }
              ],
              "location": "butonlar.butonaTikla(String)"
            },
            "keyword": "* ",
            "BDD_STEP_UUID": "23db0de9-ad03-493d-97cd-1e97531a1c55"
          },
          {
            "result": {
              "duration": 512649700,
              "status": "passed"
            },
            "line": 37,
            "name": "Alt butonlardan UBL Seçilenleri İndir var mı",
            "match": {
              "arguments": [
                {
                  "val": "UBL Seçilenleri İndir",
                  "offset": 16
                }
              ],
              "location": "butonlar.altButonVarMi(String)"
            },
            "keyword": "* ",
            "BDD_STEP_UUID": "1937e190-8e49-4516-a517-3388f99883a4"
          },
          {
            "result": {
              "duration": 391221700,
              "status": "passed"
            },
            "line": 38,
            "name": "Alt butonlardan UBL Tümünü İndir var mı",
            "match": {
              "arguments": [
                {
                  "val": "UBL Tümünü İndir",
                  "offset": 16
                }
              ],
              "location": "butonlar.altButonVarMi(String)"
            },
            "keyword": "* ",
            "BDD_STEP_UUID": "a2c2fe68-9eb1-47d1-bf9c-9128ca2de65e"
          },
          {
            "result": {
              "duration": 520394300,
              "status": "passed"
            },
            "line": 39,
            "name": "Butonlardan UBL isimli butona tıklanır",
            "match": {
              "arguments": [
                {
                  "val": "UBL",
                  "offset": 12
                }
              ],
              "location": "butonlar.butonaTikla(String)"
            },
            "keyword": "* ",
            "BDD_STEP_UUID": "91f9a353-4570-45f5-871a-415982e621e8"
          },
          {
            "result": {
              "duration": 529329100,
              "status": "passed"
            },
            "line": 40,
            "name": "Alt butonlardan Göster var mı",
            "match": {
              "arguments": [
                {
                  "val": "Göster",
                  "offset": 16
                }
              ],
              "location": "butonlar.altButonVarMi(String)"
            },
            "keyword": "* ",
            "BDD_STEP_UUID": "dcde9a5f-e2d5-40bc-ab84-ceebffa4205b"
          },
          {
            "result": {
              "duration": 437245200,
              "status": "passed"
            },
            "line": 41,
            "name": "Alt butonlardan İndir var mı",
            "match": {
              "arguments": [
                {
                  "val": "İndir",
                  "offset": 16
                }
              ],
              "location": "butonlar.altButonVarMi(String)"
            },
            "keyword": "* ",
            "BDD_STEP_UUID": "bd2d52a5-c1d7-4f51-b42a-4c33d1f27665"
          },
          {
            "result": {
              "duration": 4097286700,
              "status": "passed"
            },
            "line": 42,
            "name": "Kullanıcı işlemlerinden Çıkış seçilir",
            "match": {
              "arguments": [
                {
                  "val": "Çıkış",
                  "offset": 24
                }
              ],
              "location": "kullaniciIslemleri.kullaniciIslemi(String)"
            },
            "keyword": "* ",
            "BDD_STEP_UUID": "e147afce-83a5-4625-8bf9-1c1f578a66ce"
          }
        ]
      }
    ],
    "name": "Giden Kutusu Irsaliye Yanitlari Buton Kontrolu",
    "description": "",
    "id": "giden-kutusu-ırsaliye-yanitlari-buton-kontrolu",
    "keyword": "Feature",
    "uri": "C:/Users/DELL/Documents/GitHub/EES_KatalonLogo/Include/features/e-Irsaliye/Giden Kutusu/Irsaliye Yanitlari/Ekran Kontrolu.feature",
    "tags": []
  }
]